8to1Mux/synthesized_outputTechIndependent.v
/* Generated by Yosys 0.41+126 (git sha1 855ac285f, g++ 11.4.0-1ubuntu1~22.04 -fPIC -Os) */

module mux_8to1(in, sel, out);
  wire _00_;
  wire _01_;
  wire _02_;
  wire _03_;
  wire _04_;
  wire _05_;
  input [7:0] in;
  wire [7:0] in;
  output out;
  wire out;
  input [2:0] sel;
  wire [2:0] sel;
  assign _00_ = sel[2] ? in[7] : in[3];
  assign _01_ = sel[2] ? in[6] : in[2];
  assign _02_ = sel[0] ? _00_ : _01_;
  assign _03_ = sel[2] ? in[5] : in[1];
  assign _04_ = sel[2] ? in[4] : in[0];
  assign _05_ = sel[0] ? _03_ : _04_;
  assign out = sel[1] ? _02_ : _05_;
endmodule

8to1Mux/tb8t1Mux.v
//Testbench for 8_to_1 Multiplexer

module tb_mux8to1;
    //Testbench signals
    reg [7:0] in;
    reg [2:0] sel;
    wire out;


    //Instantiate the 8-to-1 multiplexer
    mux_8to1 uut(.in(in),.sel(sel),.out(out));

    //Dump file for GTKWave
    initial begin
        $dumpfile("mux8to1.vcd");
        $dumpvars(0, tb_mux8to1);
    end

    //Test procedures
    initial begin
        //Apply test vectors
        in=8'b10101010;
        sel=3'b000; #10;
        sel=3'b001; #10;
        sel=3'b010; #10;
        sel=3'b011; #10;
        sel=3'b100; #10;
        sel=3'b101; #10;
        sel=3'b110; #10;
        sel=3'b111; #10;

        //Finish simulation
        $finish;
    end
    endmodule

8to1Mux/mux8to1.vcd
$date
	Thu Oct 10 19:31:18 2024
$end
$version
	Icarus Verilog
$end
$timescale
	1s
$end
$scope module tb_mux8to1 $end
$var wire 1 ! out $end
$var reg 8 " in [7:0] $end
$var reg 3 # sel [2:0] $end
$scope module uut $end
$var wire 8 $ in [7:0] $end
$var wire 3 % sel [2:0] $end
$var reg 1 ! out $end
$upscope $end
$upscope $end
$enddefinitions $end
$comment Show the parameter values. $end
$dumpall
$end
#0
$dumpvars
b0 %
b10101010 $
b0 #
b10101010 "
0!
$end
#10
1!
b1 #
b1 %
#20
0!
b10 #
b10 %
#30
1!
b11 #
b11 %
#40
0!
b100 #
b100 %
#50
1!
b101 #
b101 %
#60
0!
b110 #
b110 %
#70
1!
b111 #
b111 %
