fullAdder/halfAdder.v
module halfAdder(input A, B, output sum, carry);
    assign sum=A ^ B;
    assign carry= A & B;
    endmodule

fullAdder/fullAdder.v
module fullAdder(input i1, i2, Cin, output Cout, sum);
    wire S, c1, c2;
    
    halfAdder HA1(.A(i1), .B(i2), .sum(S), .carry(c1));
    halfAdder HA2(.A(S), .B(Cin), .sum(sum), .carry(c2));
    or orGate(Cout, c1, c2);
    endmodule

fullAdder/tbFullAdder.v
module tbfullAdder;

// Signals
    reg i1, i2, Cin;
    wire Cout, sum;

//instance of fullAdder
    fullAdder fa(.i1(i1), .i2(i2), .Cin(Cin), .Cout(Cout), .sum(sum));


    initial begin
        i1=0; i2=0; Cin=0;
        #10;

        i1=0; i2=0; Cin=0;  #10;
        i1=1; i2=0; Cin=0;  #10;
        i1=0; i2=1; Cin=0;  #10;
        i1=0; i2=0; Cin=1;  #10;
        i1=1; i2=1; Cin=0;  #10;
        i1=1; i2=0; Cin=1;  #10;
        i1=0; i2=1; Cin=1;  #10;
        i1=1; i2=1; Cin=1;  #10;

        $finish;
    end

    initial begin
        $dumpfile ("tbFullAdder.vcd");
        $dumpvars (0,tbfullAdder);
    end
    endmodule

fullAdder/tbFullAdder.vcd
$date
	Tue Jul  2 12:34:59 2024
$end
$version
	Icarus Verilog
$end
$timescale
	1s
$end
$scope module tbfullAdder $end
$var wire 1 ! sum $end
$var wire 1 " Cout $end
$var reg 1 # Cin $end
$var reg 1 $ i1 $end
$var reg 1 % i2 $end
$scope module fa $end
$var wire 1 # Cin $end
$var wire 1 " Cout $end
$var wire 1 $ i1 $end
$var wire 1 % i2 $end
$var wire 1 ! sum $end
$var wire 1 & c2 $end
$var wire 1 ' c1 $end
$var wire 1 ( S $end
$scope module HA1 $end
$var wire 1 $ A $end
$var wire 1 % B $end
$var wire 1 ' carry $end
$var wire 1 ( sum $end
$upscope $end
$scope module HA2 $end
$var wire 1 ( A $end
$var wire 1 # B $end
$var wire 1 & carry $end
$var wire 1 ! sum $end
$upscope $end
$upscope $end
$upscope $end
$enddefinitions $end
$comment Show the parameter values. $end
$dumpall
$end
#0
$dumpvars
0(
0'
0&
0%
0$
0#
0"
0!
$end
#20
1!
1(
1$
#30
1%
0$
#40
0(
1#
0%
#50
1"
0!
1'
0#
1%
1$
#60
1&
1(
0'
1#
0%
#70
1%
0$
#80
1!
0&
0(
1'
1$
