3t8 decoder/decoder.v
module decoder(x, y, z, d0, d1, d2, d3, d4, d5, d6, d7);
  input x, y, z; // Data inputs
  output d0, d1, d2, d3, d4, d5, d6, d7; // Output

   // Using AND gates for each minterm
    assign d0 = ~x & ~y & ~z; // Minterm 0
    assign d1 = ~x & ~y & z;   // Minterm 1
    assign d2 = ~x & y & ~z;  // Minterm 2
    assign d3 = ~x & y & z;    // Minterm 3
    assign d4 = x & ~y & ~z;  // Minterm 4
    assign d5 = x & ~y & z;    // Minterm 5
    assign d6 = x & y & ~z;  // Minterm 6
    assign d7 = x & y & z;    // Minterm 7

endmodule

3t8 decoder/testbench_decoder.v
module testbench ( );

  // Inputs and Outputs
  reg [2:0] in;
  wire [7:0] out;

  // DUT instantiation
  decoder dut (
    .x(in[2]),
	.y(in[1]),
	.z(in[0]),
	.d0(out[7]),
	.d1(out[6]),
	.d2(out[5]),
	.d3(out[4]),
	.d4(out[3]),
	.d5(out[2]),
	.d6(out[1]),
	.d7(out[0])
  );

  // Clock and reset signals
  reg clk;
  reg rst;

  // Initial values
  initial begin
    clk = 0;
    rst = 1;
    #20;
    rst = 0;
  end

  // Clock generator
  always begin
    #10 clk = ~clk;
  end

  initial begin
      $dumpvars(0,testbench);
      $dumpfile("vardump.vcd");
  end

  // Test sequence
  reg [3:0] i;
  always @(posedge clk, posedge rst) begin
    if (rst) begin
      i = 0;
    end else begin
      // Apply all possible BCD values (0-9)
      in <= i;
      #20;
      i = i + 1;
      if (i == 8) $finish;
    end
    $monitor("%d: Input = %b, Output = %b", $time, in, out);
  end 

endmodule

3t8 decoder/dump.vcd
$date
	Sun Apr 13 15:40:04 2025
$end
$version
	Icarus Verilog
$end
$timescale
	1s
$end
$scope module testbench $end
$var wire 8 ! out [7:0] $end
$var reg 1 " clk $end
$var reg 4 # i [3:0] $end
$var reg 3 $ in [2:0] $end
$var reg 1 % rst $end
$scope module dut $end
$var wire 1 & d0 $end
$var wire 1 ' d1 $end
$var wire 1 ( d2 $end
$var wire 1 ) d3 $end
$var wire 1 * d4 $end
$var wire 1 + d5 $end
$var wire 1 , d6 $end
$var wire 1 - d7 $end
$var wire 1 . x $end
$var wire 1 / y $end
$var wire 1 0 z $end
$upscope $end
$upscope $end
$enddefinitions $end
$comment Show the parameter values. $end
$dumpall
$end
#0
$dumpvars
x0
x/
x.
x-
x,
x+
x*
x)
x(
x'
x&
1%
bx $
bx #
0"
bx !
$end
#10
b0 #
1"
#20
0"
0%
#30
1&
b10000000 !
0(
0*
0,
0'
0)
0+
0-
0.
0/
00
b0 $
1"
#40
0"
#50
b1000000 !
0&
1'
10
b1 $
1"
b1 #
#60
0"
#70
b100000 !
0&
1(
0'
1/
00
b10 $
1"
b10 #
#80
0"
#90
b10000 !
0(
1)
10
b11 $
1"
b11 #
#100
0"
#110
b1000 !
1*
0)
1.
0/
00
b100 $
1"
b100 #
#120
0"
#130
b100 !
0*
1+
10
b101 $
1"
b101 #
#140
0"
#150
b10 !
0*
1,
0+
1/
00
b110 $
1"
b110 #
#160
0"
#170
b1 !
0,
1-
10
b111 $
1"
b111 #
#180
0"
#190
1"
b1000 #
