fullAdder/halfAdder.v
module halfAdder(input A, B, output sum, carry);
    assign sum=A ^ B;
    assign carry= A & B;
    endmodule

2BitMultiplier/multplr2bit.v
module multiplier( input [1:0]A, B, output [3:0]product);
    wire  a1, a2, b1, b2;
    and (product[0], A[0], B[0]);
    and (a1, B[0], A[1]);
    and (a2, B[1], A[0]);
    halfAdder instance1 (.A(a1), .B(a2), .carry(b1), .sum(product[1]));
    and (b2, B[1], A[1]);
    halfAdder instance2 (.A(b1), .B(b2), .sum(product[2]), .carry(product[3]));
    endmodule

2BitMultiplier/tbMultiplier.v
module tbMultiplier;

//Signals
    reg [1:0]A, B;
    wire [3:0] product;

//Module instantiation
    multiplier instanceM (.A(A), .B(B), .product(product));
    
    initial begin
        A[1]=0; A[0]=0; B[1]= 0; B[0]= 0; #10 
        A[1]=0; A[0]=0; B[1]= 0; B[0]= 1; #10 
        A[1]=0; A[0]=0; B[1]= 1; B[0]= 0; #10 
        A[1]=0; A[0]=0; B[1]= 1; B[0]= 1; #10 
        A[1]=0; A[0]=1; B[1]= 0; B[0]= 0; #10 
        A[1]=0; A[0]=1; B[1]= 0; B[0]= 1; #10 
        A[1]=0; A[0]=1; B[1]= 1; B[0]= 0; #10 
        A[1]=0; A[0]=1; B[1]= 1; B[0]= 1; #10 
        A[1]=1; A[0]=0; B[1]= 0; B[0]= 0; #10 
        A[1]=1; A[0]=0; B[1]= 0; B[0]= 1; #10 
        A[1]=1; A[0]=0; B[1]= 1; B[0]= 0; #10 
        A[1]=1; A[0]=0; B[1]= 1; B[0]= 1; #10 
        A[1]=1; A[0]=1; B[1]= 0; B[0]= 0; #10 
        A[1]=1; A[0]=1; B[1]= 0; B[0]= 1; #10 
        A[1]=1; A[0]=1; B[1]= 1; B[0]= 0; #10 
        A[1]=1; A[0]=1; B[1]= 1; B[0]= 1; #10 

        $finish;
    end

    initial begin
        $dumpfile ("tbMultiplier");
        $dumpvars (0,tbMultiplier);
    end
    endmodule

2BitMultiplier/tbMultiplier.vcd
$date
	Thu Jul  4 22:56:48 2024
$end
$version
	Icarus Verilog
$end
$timescale
	1s
$end
$scope module tbMultiplier $end
$var wire 4 ! product [3:0] $end
$var reg 2 " A [1:0] $end
$var reg 2 # B [1:0] $end
$scope module instanceM $end
$var wire 2 $ A [1:0] $end
$var wire 2 % B [1:0] $end
$var wire 1 & a1 $end
$var wire 1 ' a2 $end
$var wire 1 ( b2 $end
$var wire 4 ) product [3:0] $end
$var wire 1 * b1 $end
$scope module instance1 $end
$var wire 1 & A $end
$var wire 1 ' B $end
$var wire 1 * carry $end
$var wire 1 + sum $end
$upscope $end
$scope module instance2 $end
$var wire 1 * A $end
$var wire 1 ( B $end
$var wire 1 , carry $end
$var wire 1 - sum $end
$upscope $end
$upscope $end
$upscope $end
$enddefinitions $end
$comment Show the parameter values. $end
$dumpall
$end
#0
$dumpvars
0-
0,
0+
0*
b0 )
0(
0'
0&
b0 %
b0 $
b0 #
b0 "
b0 !
$end
#10
b1 #
b1 %
#20
b10 #
b10 %
#30
b11 #
b11 %
#40
b0 #
b0 %
b1 "
b1 $
#50
b1 !
b1 )
b1 #
b1 %
#60
b10 !
b10 )
1+
1'
b10 #
b10 %
#70
b11 !
b11 )
b11 #
b11 %
#80
b0 !
b0 )
0+
0'
b0 #
b0 %
b10 "
b10 $
#90
b10 !
b10 )
1+
1&
b1 #
b1 %
#100
b100 !
b100 )
0+
1-
0&
1(
b10 #
b10 %
#110
b110 !
b110 )
1+
1&
b11 #
b11 %
#120
b0 !
b0 )
0+
0-
0&
0(
b0 #
b0 %
b11 "
b11 $
#130
b11 !
b11 )
1+
1&
b1 #
b1 %
#140
b110 !
b110 )
1-
0&
1'
1(
b10 #
b10 %
#150
0-
1,
b1001 !
b1001 )
0+
1*
1&
b11 #
b11 %
