priority encoder/priorityEnc.v
module priority_encoder(p0, p1, p2, p3, p4, p5, p6, p7, z1, z2, z4);
  input p0, p1, p2, p3, p4, p5, p6, p7; // Data inputs
  output z1, z2, z4; // Output

  assign z1 = (p1 & ~p2 & ~p4 & ~p6) | (p3 & ~p4 & ~p6) | (p5 & ~p6) | p7;
  assign z2 = (p2 & ~p4 & ~p5) | (p3 & ~p4 & ~p5) | p6 | p7;
  assign z4 =  p4 | p5 | p6 | p7;
endmodule

priority encoder/testbench_priorityEnc.v
module testbench (
  );

  // Inputs and Outputs
  reg [7:0] in;
  wire [2:0] out;

  // DUT instantiation
  priority_encoder dut (
    .p0(in[7]),
	.p1(in[6]),
	.p2(in[5]),
	.p3(in[4]),
	.p4(in[3]),
	.p5(in[2]),
	.p6(in[1]),
	.p7(in[0]),
	.z1(out[0]),
	.z2(out[1]),
	.z4(out[2])	
  );

  // Clock and reset signals
  reg clk;
  reg rst;

  // Initial values
  initial begin
    clk = 0;
    rst = 1;
    #20;
    rst = 0;
  end

  // Clock generator
  always begin
    #10 clk = ~clk;
  end
  
  initial begin
      $dumpvars(0,testbench);
      $dumpfile("vardump.vcd");
  end

  // Test sequence
  reg [3:0] i;
  always @(posedge clk, posedge rst) begin
    if (rst) begin
      i = 0;
    end else begin
      // Apply all possible BCD values (0-9)
      in <= $random%256;
      #20;
      i = i + 1;
      if (i == 10) $finish;
    end
    $monitor("%d: Input = %b, Output = %b", $time, in, out);
  end 

endmodule

priority encoder/dump.vcd
$date
	Sun Apr 13 15:56:43 2025
$end
$version
	Icarus Verilog
$end
$timescale
	1s
$end
$scope module testbench $end
$var wire 3 ! out [2:0] $end
$var reg 1 " clk $end
$var reg 4 # i [3:0] $end
$var reg 8 $ in [7:0] $end
$var reg 1 % rst $end
$scope module dut $end
$var wire 1 & p0 $end
$var wire 1 ' p1 $end
$var wire 1 ( p2 $end
$var wire 1 ) p3 $end
$var wire 1 * p4 $end
$var wire 1 + p5 $end
$var wire 1 , p6 $end
$var wire 1 - p7 $end
$var wire 1 . z1 $end
$var wire 1 / z2 $end
$var wire 1 0 z4 $end
$upscope $end
$upscope $end
$enddefinitions $end
$comment Show the parameter values. $end
$dumpall
$end
#0
$dumpvars
x0
x/
x.
x-
x,
x+
x*
x)
x(
x'
x&
1%
bx $
bx #
0"
bx !
$end
#10
b0 #
1"
#20
0"
0%
#30
0/
b101 !
1.
10
0&
0'
1(
0)
0*
1+
0,
0-
b100100 $
1"
#40
0"
#50
b111 !
1/
1&
0(
0+
1-
b10000001 $
1"
b1 #
#60
0"
#70
0&
1*
b1001 $
1"
b10 #
#80
0"
#90
1'
1(
0*
1,
b1100011 $
1"
b11 #
#100
0"
#110
0'
0(
1*
1+
0,
b1101 $
1"
b100 #
#120
0"
#130
1&
b10001101 $
1"
b101 #
#140
0"
#150
0&
1'
1(
0*
b1100101 $
1"
b110 #
#160
0"
#170
0.
b110 !
1/
0'
0(
1)
0+
1,
0-
b10010 $
1"
b111 #
#180
0"
#190
b111 !
1.
0)
0,
1-
b1 $
1"
b1000 #
#200
0"
#210
1*
1+
b1101 $
1"
b1001 #
#220
0"
#230
1"
b1010 #
