BCD to Excess 3/bcdToExcess3.v
module BCD_to_Excess3(
  input A, B, C, D,
  output z, w, x, y
);
  assign z = ~D; 
  assign y = (C & D) | (~C & ~D);
  assign x = (~B & C) | (~B & D) | (B & ~C & ~D);
  assign w = A | (B & C) | (B & D); 
endmodule

BCD to Excess/testbench_BE.v
module testbench (
  );

  // Inputs and Outputs
  reg [3:0] bcd;
  wire [3:0] excess3;

  // DUT instantiation
  BCD_to_Excess3 dut (
    .A(bcd[3]),
    .B(bcd[2]),
    .C(bcd[1]),
    .D(bcd[0]),
    .w(excess3[3]),
    .x(excess3[2]),
    .y(excess3[1]),
    .z(excess3[0])
  );

  // Clock and reset signals
  reg clk;
  reg rst;
  
  initial begin
    clk = 0;
    rst = 1;
    #20;
    rst = 0;
  end

  initial begin
      $dumpvars(0,testbench);
      $dumpfile("vardump.vcd");
   end

  // Clock generator
  always begin
    #10 clk = ~clk;
  end

  // Test sequence
  reg [3:0] i;
  always @(posedge clk, posedge rst) begin
    if (rst) begin
      i = 0;
    end else begin
      // Apply all possible BCD values (0-9)
      bcd <= i;
      #20;
      i = i + 1;
      if (i == 10) $finish;
    end
    $monitor("%d: BCD = %b, Excess-3 = %b", $time, bcd, excess3);
  end 

endmodule

BCD to Excess/vardump.vcd
$date
	Sun Apr 13 14:37:03 2025
$end
$version
	Icarus Verilog
$end
$timescale
	1s
$end
$scope module testbench $end
$var wire 4 ! excess3 [3:0] $end
$var reg 4 " bcd [3:0] $end
$var reg 1 # clk $end
$var reg 4 $ i [3:0] $end
$var reg 1 % rst $end
$scope module dut $end
$var wire 1 & A $end
$var wire 1 ' B $end
$var wire 1 ( C $end
$var wire 1 ) D $end
$var wire 1 * w $end
$var wire 1 + x $end
$var wire 1 , y $end
$var wire 1 - z $end
$upscope $end
$upscope $end
$enddefinitions $end
$comment Show the parameter values. $end
$dumpall
$end
#0
$dumpvars
x-
x,
x+
x*
x)
x(
x'
x&
1%
bx $
0#
bx "
bx !
$end
#10
b0 $
1#
#20
0#
0%
#30
0+
b11 !
1,
0*
1-
0&
0'
0(
0)
b0 "
1#
#40
0#
#50
0,
1+
b100 !
0-
1)
b1 "
1#
b1 $
#60
0#
#70
b101 !
1-
1(
0)
b10 "
1#
b10 $
#80
0#
#90
b110 !
1,
0-
1)
b11 "
1#
b11 $
#100
0#
#110
b111 !
1-
1'
0(
0)
b100 "
1#
b100 $
#120
0#
#130
0,
0+
b1000 !
1*
0-
1)
b101 "
1#
b101 $
#140
0#
#150
0+
b1001 !
1*
1-
1(
0)
b110 "
1#
b110 $
#160
0#
#170
b1010 !
1,
0-
1)
b111 "
1#
b111 $
#180
0#
#190
b1011 !
1-
1&
0'
0(
0)
b1000 "
1#
b1000 $
#200
0#
#210
0,
1+
b1100 !
0-
1)
b1001 "
1#
b1001 $
#220
0#
#230
1#
b1010 $
