Finite State Machines/Serial Parity detector/parity_gen.v
module parity_gen (x, clk, z);
    input x, clk;
    output reg z;
    reg even_odd;   //The machine state
    parameter EVEN=0, ODD=1;

    always @(posedge clk)
        case (even_odd)
            EVEN: begin
                z <= x ? 1:0;
                even_odd <= x ? ODD:EVEN;
            end

            ODD: begin
                z <= x ? 0:1;
                even_odd <= x ? EVEN:ODD;
            end

            default:
                even_odd <=EVEN;
        endcase
        endmodule

Finite State Machines/Serial Parity detector/test_parity.v
module test_parity;
    reg clk, x;
    wire z;
    parity_gen par(x, clk, z);

    initial
    begin
        $dumpfile ("parity.vcd");
        $dumpvars (0, test_parity);
        clk = 1'b0;
    end

    always #5 clk = ~clk;

    initial
    begin
        #2 x=0; #10 x=1; #10 x=1; #10 x=1;
        #10 x=0; #10 x=1; #10 x=1; #10 x=0;
        #10 x=0; #10 x=1; #10 x=1; #10 x=0;
        #10 $finish;
    end
    endmodule

Finite State Machines/Serial Parity detector/parity.vcd
$date
	Fri Aug 30 20:25:58 2024
$end
$version
	Icarus Verilog
$end
$timescale
	1s
$end
$scope module test_parity $end
$var wire 1 ! z $end
$var reg 1 " clk $end
$var reg 1 # x $end
$scope module par $end
$var wire 1 " clk $end
$var wire 1 # x $end
$var parameter 32 $ EVEN $end
$var parameter 32 % ODD $end
$var reg 1 & even_odd $end
$var reg 1 ! z $end
$upscope $end
$upscope $end
$enddefinitions $end
$comment Show the parameter values. $end
$dumpall
b1 %
b0 $
$end
#0
$dumpvars
x&
x#
0"
x!
$end
#2
0#
#5
0&
1"
#10
0"
#12
1#
#15
1&
1!
1"
#20
0"
#25
0&
0!
1"
#30
0"
#35
1&
1!
1"
#40
0"
#42
0#
#45
1"
#50
0"
#52
1#
#55
0&
0!
1"
#60
0"
#65
1&
1!
1"
#70
0"
#72
0#
#75
1"
#80
0"
#85
1"
#90
0"
#92
1#
#95
0&
0!
1"
#100
0"
#105
1&
1!
1"
#110
0"
#112
0#
