FullAdderFlow/FA_RTL.v
// RTL description of Full Adder in verilog

module FA(A, B , Cin, Sum, Cout);
  input A, B, Cin;
  output Sum, Cout;

  assign Sum = A^B^Cin;
  assign Cout = (A&B)|(Cin&(A^B));
  endmodule

FullAdderFlow/FA_RTL_tb.v
//Testbench for the RTL decsription of fulladder

module tbFA;

    //Signals 
    reg a,b,cin;
    wire Cout, sum;

    //instance of fullAdder
    FA instFA(.A(a), .B(b), .Cin(cin), .Cout(Cout), .Sum(sum));

    initial begin
        a=0; b=0; cin=0;
        #10;

        a=0; b=0; cin=0;  #10;
        a=1; b=0; cin=0;  #10;
        a=0; b=1; cin=0;  #10;
        a=0; b=0; cin=1;  #10;
        a=1; b=1; cin=0;  #10;
        a=1; b=0; cin=1;  #10;
        a=0; b=1; cin=1;  #10;
        a=1; b=1; cin=1;  #10;

        $finish;
    end

    initial begin
        $dumpfile ("tb_FA.vcd");
        $dumpvars(0,tbFA);
    end
    endmodule

FullAdderFlow/tb_FA.vcd
$date
	Fri Oct 11 14:16:47 2024
$end
$version
	Icarus Verilog
$end
$timescale
	1s
$end
$scope module tbFA $end
$var wire 1 ! sum $end
$var wire 1 " Cout $end
$var reg 1 # a $end
$var reg 1 $ b $end
$var reg 1 % cin $end
$scope module instFA $end
$var wire 1 # A $end
$var wire 1 $ B $end
$var wire 1 % Cin $end
$var wire 1 " Cout $end
$var wire 1 ! Sum $end
$upscope $end
$upscope $end
$enddefinitions $end
$comment Show the parameter values. $end
$dumpall
$end
#0
$dumpvars
0%
0$
0#
0"
0!
$end
#20
1!
1#
#30
1$
0#
#40
1%
0$
#50
1"
0!
0%
1$
1#
#60
1%
0$
#70
1$
0#
#80
1!
1#
